LICENSE.txt
setup.cfg
setup.py
docs/html/api-objects.txt
docs/html/class-tree.html
docs/html/crarr.png
docs/html/epydoc.css
docs/html/epydoc.js
docs/html/exceptions.AssertionError-class.html
docs/html/frames.html
docs/html/help.html
docs/html/identifier-index.html
docs/html/index.html
docs/html/module-tree.html
docs/html/redirect.html
docs/html/simplexmlapi-module.html
docs/html/simplexmlapi-pysrc.html
docs/html/simplexmlapi.api-module.html
docs/html/simplexmlapi.api-pysrc.html
docs/html/simplexmlapi.api.SimpleXmlApi-class.html
docs/html/simplexmlapi.node-module.html
docs/html/simplexmlapi.node-pysrc.html
docs/html/simplexmlapi.node.AttributeParsingError-class.html
docs/html/simplexmlapi.node.DotNode-class.html
docs/html/simplexmlapi.node.DotNodeAttribute-class.html
docs/html/simplexmlapi.node.DotNodeList-class.html
docs/html/simplexmlapi.node.DotNodeParent-class.html
docs/html/simplexmlapi.node.DotXMLDoc-class.html
docs/html/simplexmlapi.node.NoSuchAttribute-class.html
docs/html/simplexmlapi.node.NoSuchNode-class.html
docs/html/simplexmlapi.tests-module.html
docs/html/simplexmlapi.tests-pysrc.html
docs/html/simplexmlapi.tests.test_api-module.html
docs/html/simplexmlapi.tests.test_api-pysrc.html
docs/html/simplexmlapi.tests.test_api.TestAPI-class.html
docs/html/simplexmlapi.tests.test_dotnode-module.html
docs/html/simplexmlapi.tests.test_dotnode-pysrc.html
docs/html/simplexmlapi.tests.test_dotnode.TestDotNodes-class.html
docs/html/toc-everything.html
docs/html/toc-simplexmlapi-module.html
docs/html/toc-simplexmlapi.api-module.html
docs/html/toc-simplexmlapi.node-module.html
docs/html/toc-simplexmlapi.tests-module.html
docs/html/toc-simplexmlapi.tests.test_api-module.html
docs/html/toc-simplexmlapi.tests.test_dotnode-module.html
docs/html/toc.html
ez_setup/README.txt
ez_setup/__init__.py
simplexmlapi/__init__.py
simplexmlapi/api.py
simplexmlapi/node.py
simplexmlapi.egg-info/PKG-INFO
simplexmlapi.egg-info/SOURCES.txt
simplexmlapi.egg-info/dependency_links.txt
simplexmlapi.egg-info/top_level.txt
simplexmlapi.egg-info/zip-safe
simplexmlapi/tests/__init__.py
simplexmlapi/tests/test_api.py
simplexmlapi/tests/test_dotnode.py