Metadata-Version: 1.0
Name: simplexmlapi
Version: 0.1.2
Summary: Simple, fast way to create read-only APIs for XML data
Home-page: http://code.google.com/p/simplexmlapi/
Author: Ian McCracken
Author-email: ian.mccracken@gmail.com
License: MIT License
Platform: any
Classifier: Topic :: Software Development :: Libraries :: Python Modules
Classifier: Intended Audience :: Developers
Classifier: License :: OSI Approved :: MIT License
Classifier: Programming Language :: Python
